{
  "name": "UniversityRequirements0_407044ef-beae-42e7-b648-6a27013a360d",
  "displayName": "UniversityRequirements0_407044ef-beae-42e7-b648-6a27013a360d",
  "description": "",
  "author": "",
  "website": "",
  "version": "",
  "issetuprecipe": false,
  "categories": "",
  "tags": [],
  "steps": [
    {
      "name": "ContentNoCache",
      "data": [
  {
    "TitlePart": {
      "Title": "2 or 3 A levels incl M"
    },
    "UniversityRequirement": {
      "Description": {
        "Html": "\u003Cp\u003E2 or 3 A levels, or equivalent, including maths\u003C/p\u003E"
      }
    },
    "GraphSyncPart": {
      "Text": "\u003C\u003Ccontentapiprefix\u003E\u003E/universityrequirement/6cddeb17-03dd-4afd-8660-8426e977d0c2"
    },
    "ContentItemId": "40782dwvt0gvvypwpsxbdvp7n7",
    "ContentItemVersionId": "4r2pq94k4n0xs5kt11kezh4746",
    "ContentType": "UniversityRequirement",
    "DisplayText": "2 or 3 A levels incl M",
    "Latest": true,
    "Published": true,
    "ModifiedUtc": "2021-04-29T19:25:19.0484610Z",
    "PublishedUtc": "2021-04-29T19:25:19.0484610Z",
    "CreatedUtc": "2021-04-29T19:25:19.0484610Z",
    "Owner": "admin",
    "Author": "admin"
  },
  {
    "TitlePart": {
      "Title": "Audition"
    },
    "UniversityRequirement": {
      "Description": {
        "Html": "\u003Cp\u003Eto pass an audition\u003C/p\u003E"
      }
    },
    "GraphSyncPart": {
      "Text": "\u003C\u003Ccontentapiprefix\u003E\u003E/universityrequirement/84d280f7-d063-4ddc-87a8-f3a03d31d8dc"
    },
    "ContentItemId": "4ab6p4ryc1djn3nbh29mw676ct",
    "ContentItemVersionId": "46ft34kks1wvzxfgcwabn76fd3",
    "ContentType": "UniversityRequirement",
    "DisplayText": "Audition",
    "Latest": true,
    "Published": true,
    "ModifiedUtc": "2021-04-29T19:25:19.0484610Z",
    "PublishedUtc": "2021-04-29T19:25:19.0484610Z",
    "CreatedUtc": "2021-04-29T19:25:19.0484610Z",
    "Owner": "admin",
    "Author": "admin"
  },
  {
    "TitlePart": {
      "Title": "5 GCSEs 9-4 incl E-M-S"
    },
    "UniversityRequirement": {
      "Description": {
        "Html": "\u003Cp\u003E5 GCSEs at grades 9 to 4 (A* to C), or equivalent, including English, maths and science\u003C/p\u003E"
      }
    },
    "GraphSyncPart": {
      "Text": "\u003C\u003Ccontentapiprefix\u003E\u003E/universityrequirement/3329fa7d-e8df-44dd-9f00-668c4985e6eb"
    },
    "ContentItemId": "4g1yfz9a33wwpsjpmd3bfjjcdw",
    "ContentItemVersionId": "4xb283j2w9cshw4qykghc722dq",
    "ContentType": "UniversityRequirement",
    "DisplayText": "5 GCSEs 9-4 incl E-M-S",
    "Latest": true,
    "Published": true,
    "ModifiedUtc": "2021-04-29T19:25:19.0484610Z",
    "PublishedUtc": "2021-04-29T19:25:19.0484610Z",
    "CreatedUtc": "2021-04-29T19:25:19.0484610Z",
    "Owner": "admin",
    "Author": "admin"
  },
  {
    "TitlePart": {
      "Title": "Foundation degree or HND standard entry"
    },
    "UniversityRequirement": {
      "Description": {
        "Html": "\u003Cp\u003E1 or 2 A levels, or equivalent, for a foundation degree or higher national diploma\u003C/p\u003E"
      }
    },
    "GraphSyncPart": {
      "Text": "\u003C\u003Ccontentapiprefix\u003E\u003E/universityrequirement/60715fd1-82d3-4f8e-bbb8-d89c86a27ed2"
    },
    "ContentItemId": "4tjk96t15rn0z27k47yxgnxtdh",
    "ContentItemVersionId": "4psyffq6emekm1pw28n2qprqx3",
    "ContentType": "UniversityRequirement",
    "DisplayText": "Foundation degree or HND standard entry",
    "Latest": true,
    "Published": true,
    "ModifiedUtc": "2021-04-29T19:25:19.0484610Z",
    "PublishedUtc": "2021-04-29T19:25:19.0484610Z",
    "CreatedUtc": "2021-04-29T19:25:19.0484610Z",
    "Owner": "admin",
    "Author": "admin"
  },
  {
    "TitlePart": {
      "Title": "Foundation degree - standard entry reqs"
    },
    "UniversityRequirement": {
      "Description": {
        "Html": "\u003Cp\u003Eat least 1 A level, or equivalent, for a foundation degree\u003C/p\u003E"
      }
    },
    "GraphSyncPart": {
      "Text": "\u003C\u003Ccontentapiprefix\u003E\u003E/universityrequirement/e5de303b-fa7d-4bd7-a3b0-7ad1f6e0e945"
    },
    "ContentItemId": "4c3emzjjdkwphz975f9f07accj",
    "ContentItemVersionId": "4yymr2g7k2zm4st8dfm4qw1e53",
    "ContentType": "UniversityRequirement",
    "DisplayText": "Foundation degree - standard entry reqs",
    "Latest": true,
    "Published": true,
    "ModifiedUtc": "2021-04-29T19:25:19.0484610Z",
    "PublishedUtc": "2021-04-29T19:25:19.0484610Z",
    "CreatedUtc": "2021-04-29T19:25:19.0484610Z",
    "Owner": "admin",
    "Author": "admin"
  },
  {
    "TitlePart": {
      "Title": "2 or 3 A levels incl M-Phy"
    },
    "UniversityRequirement": {
      "Description": {
        "Html": "\u003Cp\u003E2 or 3 A levels, or equivalent, including maths and physics\u003C/p\u003E"
      }
    },
    "GraphSyncPart": {
      "Text": "\u003C\u003Ccontentapiprefix\u003E\u003E/universityrequirement/5ee33a13-da28-4140-863c-79b3534c0fd4"
    },
    "ContentItemId": "40swqmqwc2jx6vyqqfw8m3jed0",
    "ContentItemVersionId": "4tz4emc6tpatyy6wvkr858x9mt",
    "ContentType": "UniversityRequirement",
    "DisplayText": "2 or 3 A levels incl M-Phy",
    "Latest": true,
    "Published": true,
    "ModifiedUtc": "2021-04-29T19:25:19.0484610Z",
    "PublishedUtc": "2021-04-29T19:25:19.0484610Z",
    "CreatedUtc": "2021-04-29T19:25:19.0484610Z",
    "Owner": "admin",
    "Author": "admin"
  },
  {
    "TitlePart": {
      "Title": "Degree standard entry reqs"
    },
    "UniversityRequirement": {
      "Description": {
        "Html": "\u003Cp\u003E2 to 3 A levels, or equivalent, for a degree\u003C/p\u003E"
      }
    },
    "GraphSyncPart": {
      "Text": "\u003C\u003Ccontentapiprefix\u003E\u003E/universityrequirement/215a24e9-ecbd-40c2-a996-327b4e8e4f9a"
    },
    "ContentItemId": "4v3s88cstzddh2ff0jewthf143",
    "ContentItemVersionId": "4ssa8psmpwxzy1ycdm1d2fww56",
    "ContentType": "UniversityRequirement",
    "DisplayText": "Degree standard entry reqs",
    "Latest": true,
    "Published": true,
    "ModifiedUtc": "2021-04-29T19:25:19.0484610Z",
    "PublishedUtc": "2021-04-29T19:25:19.0484610Z",
    "CreatedUtc": "2021-04-29T19:25:19.0484610Z",
    "Owner": "admin",
    "Author": "admin"
  },
  {
    "TitlePart": {
      "Title": "Postgraduate study - relevant degree needed"
    },
    "UniversityRequirement": {
      "Description": {
        "Html": "\u003Cp\u003Ea degree in a relevant subject for postgraduate study\u003C/p\u003E"
      }
    },
    "GraphSyncPart": {
      "Text": "\u003C\u003Ccontentapiprefix\u003E\u003E/universityrequirement/118a686c-b613-4347-b6b0-d6055e265874"
    },
    "ContentItemId": "4z17azgge9b67rdb6j0f1mfb4a",
    "ContentItemVersionId": "48x7x5rjmaa5t6b7vpfxc4kwdf",
    "ContentType": "UniversityRequirement",
    "DisplayText": "Postgraduate study - relevant degree needed",
    "Latest": true,
    "Published": true,
    "ModifiedUtc": "2021-04-29T19:25:19.0484610Z",
    "PublishedUtc": "2021-04-29T19:25:19.0484610Z",
    "CreatedUtc": "2021-04-29T19:25:19.0484610Z",
    "Owner": "admin",
    "Author": "admin"
  }
      ]
    }
  ]
}