{
  "name": "RequirementsPrefixes0_eeee437a-9668-499a-93a4-4163afc1ff50",
  "displayName": "RequirementsPrefixes0_eeee437a-9668-499a-93a4-4163afc1ff50",
  "description": "",
  "author": "",
  "website": "",
  "version": "",
  "issetuprecipe": false,
  "categories": "",
  "tags": [],
  "steps": [
    {
      "name": "ContentNoCache",
      "data": [
  {
    "TitlePart": {
      "Title": "You may need:"
    },
    "RequirementsPrefix": {
      "Description": {
        "Html": "\u003Cp\u003EYou may need:\u003C/p\u003E"
      }
    },
    "GraphSyncPart": {
      "Text": "http://nationalcareers.service.gov.uk/requirementsprefix/860ab254-2a7c-4149-9972-dd26d583d6e6"
    },
    "ContentItemId": "4e7m01a3bx4r571dmgd959hw59",
    "ContentItemVersionId": "49xynwzgnczn50w498y1bpayc6",
    "ContentType": "RequirementsPrefix",
    "DisplayText": "You may need:",
    "Latest": true,
    "Published": true,
    "ModifiedUtc": "2020-05-18T14:40:35.6757770Z",
    "PublishedUtc": "2020-05-18T14:40:35.6757770Z",
    "CreatedUtc": "2020-05-18T14:40:35.6757770Z",
    "Owner": "admin",
    "Author": "admin"
  },
  {
    "TitlePart": {
      "Title": "To do this apprenticeship, you\u0027ll need:"
    },
    "RequirementsPrefix": {
      "Description": {
        "Html": "\u003Cp\u003ETo do this apprenticeship, you\u0027ll need:\u003C/p\u003E"
      }
    },
    "GraphSyncPart": {
      "Text": "http://nationalcareers.service.gov.uk/requirementsprefix/b399db44-fedf-4aff-9c38-78f507a1f5f2"
    },
    "ContentItemId": "4y7jj1qd12bjsxexv24vfmn4d3",
    "ContentItemVersionId": "40xr85yax734s4jgar1befphnr",
    "ContentType": "RequirementsPrefix",
    "DisplayText": "To do this apprenticeship, you\u0027ll need:",
    "Latest": true,
    "Published": true,
    "ModifiedUtc": "2020-05-18T14:40:35.6757770Z",
    "PublishedUtc": "2020-05-18T14:40:35.6757770Z",
    "CreatedUtc": "2020-05-18T14:40:35.6757770Z",
    "Owner": "admin",
    "Author": "admin"
  },
  {
    "TitlePart": {
      "Title": "There are no set entry requirements for this route."
    },
    "RequirementsPrefix": {
      "Description": {
        "Html": "\u003Cp\u003EThere are no set entry requirements for this route.\u003C/p\u003E"
      }
    },
    "GraphSyncPart": {
      "Text": "http://nationalcareers.service.gov.uk/requirementsprefix/cd9a806d-0b51-417b-bfb6-5359885a907c"
    },
    "ContentItemId": "4r9cf1grwa2cy4mr4kdfms5mxk",
    "ContentItemVersionId": "4w1q1tkdny9pq1f1n2dqrkv44x",
    "ContentType": "RequirementsPrefix",
    "DisplayText": "There are no set entry requirements for this route.",
    "Latest": true,
    "Published": true,
    "ModifiedUtc": "2020-05-18T14:40:35.6757770Z",
    "PublishedUtc": "2020-05-18T14:40:35.6757770Z",
    "CreatedUtc": "2020-05-18T14:40:35.6757770Z",
    "Owner": "admin",
    "Author": "admin"
  },
  {
    "TitlePart": {
      "Title": "There are no set entry requirements but it may help you to get in if you have:"
    },
    "RequirementsPrefix": {
      "Description": {
        "Html": "\u003Cp\u003EThere are no set entry requirements but it may help you to get in if you have:\u003C/p\u003E"
      }
    },
    "GraphSyncPart": {
      "Text": "http://nationalcareers.service.gov.uk/requirementsprefix/8b618a8e-16a3-4b4c-bde5-a8919d7f789e"
    },
    "ContentItemId": "49rj33qqydk5kyd1zv1phjxyde",
    "ContentItemVersionId": "46mgjn5mbk42g05kjzf2xwmcm8",
    "ContentType": "RequirementsPrefix",
    "DisplayText": "There are no set entry requirements but it may help you to get in if you have:",
    "Latest": true,
    "Published": true,
    "ModifiedUtc": "2020-05-18T14:40:35.6757770Z",
    "PublishedUtc": "2020-05-18T14:40:35.6757770Z",
    "CreatedUtc": "2020-05-18T14:40:35.6757770Z",
    "Owner": "admin",
    "Author": "admin"
  },
  {
    "TitlePart": {
      "Title": "You\u0027ll usually need:"
    },
    "RequirementsPrefix": {
      "Description": {
        "Html": "\u003Cp\u003EYou\u0027ll usually need:\u003C/p\u003E"
      }
    },
    "GraphSyncPart": {
      "Text": "http://nationalcareers.service.gov.uk/requirementsprefix/ab110d2c-898f-4bc2-9608-4ac8270e102a"
    },
    "ContentItemId": "4bxb1bsj999xr4xghdzg7s4wxa",
    "ContentItemVersionId": "4k8vfbx29g2ww1t2gq6tjfp6n0",
    "ContentType": "RequirementsPrefix",
    "DisplayText": "You\u0027ll usually need:",
    "Latest": true,
    "Published": true,
    "ModifiedUtc": "2020-05-18T14:40:35.6757770Z",
    "PublishedUtc": "2020-05-18T14:40:35.6757770Z",
    "CreatedUtc": "2020-05-18T14:40:35.6757770Z",
    "Owner": "admin",
    "Author": "admin"
  },
  {
    "TitlePart": {
      "Title": "Employers will set their own entry requirements."
    },
    "RequirementsPrefix": {
      "Description": {
        "Html": "\u003Cp\u003EEmployers will set their own entry requirements.\u003C/p\u003E"
      }
    },
    "GraphSyncPart": {
      "Text": "http://nationalcareers.service.gov.uk/requirementsprefix/7405626d-293b-437b-b76e-5e934732a231"
    },
    "ContentItemId": "41kgjf9r2n4jy0y07995cgda5n",
    "ContentItemVersionId": "4m2e976v58a7h4xysdab73d6wr",
    "ContentType": "RequirementsPrefix",
    "DisplayText": "Employers will set their own entry requirements.",
    "Latest": true,
    "Published": true,
    "ModifiedUtc": "2020-05-18T14:40:35.6757770Z",
    "PublishedUtc": "2020-05-18T14:40:35.6757770Z",
    "CreatedUtc": "2020-05-18T14:40:35.6757770Z",
    "Owner": "admin",
    "Author": "admin"
  }
      ]
    }
  ]
}