{
  "name": "JobCategories0_d7958e76-9180-451b-aab2-e255222ae93d",
  "displayName": "JobCategories0_d7958e76-9180-451b-aab2-e255222ae93d",
  "description": "",
  "author": "",
  "website": "",
  "version": "",
  "issetuprecipe": false,
  "categories": "",
  "tags": [],
  "steps": [
    {
      "name": "ContentNoCache",
      "data": [
  {
    "TitlePart": {
      "Title": "Hospitality and food"
    },
    "JobCategory": {
      "Description": {
        "Html": "\u003Cp\u003EHospitality and food\u003C/p\u003E"
      },
      "WebsiteURI": {
        "Text": "/job-categories/hospitality-and-food"
      },
      "JobProfiles": {
        "ContentItemIds": [
          "46azb3wqtk3cgs106wkrngmfmv"
        ]
      }
    },
    "GraphSyncPart": {
      "Text": "http://nationalcareers.service.gov.uk/jobcategory/eb52e78c-5455-408b-8c45-e82a53703d96"
    },
    "ContentItemId": "44fk6qcg0ctansjmsdf2xyjgd3",
    "ContentItemVersionId": "4ykp143y14aamzm4v4p95jr6xf",
    "ContentType": "JobCategory",
    "DisplayText": "Hospitality and food",
    "Latest": true,
    "Published": true,
    "ModifiedUtc": "2020-04-20T15:05:20.9665540Z",
    "PublishedUtc": "2020-04-20T15:05:20.9665540Z",
    "CreatedUtc": "2020-04-20T15:05:20.9665540Z",
    "Owner": "admin",
    "Author": "admin"
  },
  {
    "TitlePart": {
      "Title": "Engineering and maintenance"
    },
    "JobCategory": {
      "Description": {
        "Html": "\u003Cp\u003EEngineering and maintenance\u003C/p\u003E"
      },
      "WebsiteURI": {
        "Text": "/job-categories/engineering-and-maintenance"
      },
      "JobProfiles": {
        "ContentItemIds": [
          "4c6160fpj2f2v0k5ksksjpmq41",
          "4rwsas55d999gzx5asgc2s9nc1"
        ]
      }
    },
    "GraphSyncPart": {
      "Text": "http://nationalcareers.service.gov.uk/jobcategory/a2f406c7-2e41-490f-8480-c583c76d3341"
    },
    "ContentItemId": "4cbxwfsw6ek5ksxa98cbyh6bd8",
    "ContentItemVersionId": "457cemgc7my8ywtmvp1qaacbcx",
    "ContentType": "JobCategory",
    "DisplayText": "Engineering and maintenance",
    "Latest": true,
    "Published": true,
    "ModifiedUtc": "2020-04-20T15:05:20.9665540Z",
    "PublishedUtc": "2020-04-20T15:05:20.9665540Z",
    "CreatedUtc": "2020-04-20T15:05:20.9665540Z",
    "Owner": "admin",
    "Author": "admin"
  },
  {
    "TitlePart": {
      "Title": "Manufacturing"
    },
    "JobCategory": {
      "Description": {
        "Html": "\u003Cp\u003EManufacturing\u003C/p\u003E"
      },
      "WebsiteURI": {
        "Text": "/job-categories/manufacturing"
      },
      "JobProfiles": {
        "ContentItemIds": []
      }
    },
    "GraphSyncPart": {
      "Text": "http://nationalcareers.service.gov.uk/jobcategory/c539ab55-3173-4341-bcb6-6176e9ddb09e"
    },
    "ContentItemId": "489bhhbgve3m945zh5sa4khqmz",
    "ContentItemVersionId": "4n0z1ntbdhbb0661jkcvvwhbcf",
    "ContentType": "JobCategory",
    "DisplayText": "Manufacturing",
    "Latest": true,
    "Published": true,
    "ModifiedUtc": "2020-04-20T15:05:20.9665540Z",
    "PublishedUtc": "2020-04-20T15:05:20.9665540Z",
    "CreatedUtc": "2020-04-20T15:05:20.9665540Z",
    "Owner": "admin",
    "Author": "admin"
  },
  {
    "TitlePart": {
      "Title": "Sports and leisure"
    },
    "JobCategory": {
      "Description": {
        "Html": "\u003Cp\u003ESports and leisure\u003C/p\u003E"
      },
      "WebsiteURI": {
        "Text": "/job-categories/sports-and-leisure"
      },
      "JobProfiles": {
        "ContentItemIds": []
      }
    },
    "GraphSyncPart": {
      "Text": "http://nationalcareers.service.gov.uk/jobcategory/47b3220a-91ab-4990-924d-e49395e21405"
    },
    "ContentItemId": "49bks87wthy237h57gkmcapx4e",
    "ContentItemVersionId": "4f879hdf318b1xembfnnc1d8ce",
    "ContentType": "JobCategory",
    "DisplayText": "Sports and leisure",
    "Latest": true,
    "Published": true,
    "ModifiedUtc": "2020-04-20T15:05:20.9665540Z",
    "PublishedUtc": "2020-04-20T15:05:20.9665540Z",
    "CreatedUtc": "2020-04-20T15:05:20.9665540Z",
    "Owner": "admin",
    "Author": "admin"
  },
  {
    "TitlePart": {
      "Title": "Beauty and wellbeing"
    },
    "JobCategory": {
      "Description": {
        "Html": "\u003Cp\u003EBeauty and wellbeing\u003C/p\u003E"
      },
      "WebsiteURI": {
        "Text": "/job-categories/beauty-and-wellbeing"
      },
      "JobProfiles": {
        "ContentItemIds": []
      }
    },
    "GraphSyncPart": {
      "Text": "http://nationalcareers.service.gov.uk/jobcategory/7b7e7855-0e6a-479d-a277-676d6f893b91"
    },
    "ContentItemId": "40ca0qs0r407c70r3mwjtb6n4c",
    "ContentItemVersionId": "4shsp3tjzy9y43k0h4a5mxg6m9",
    "ContentType": "JobCategory",
    "DisplayText": "Beauty and wellbeing",
    "Latest": true,
    "Published": true,
    "ModifiedUtc": "2020-04-20T15:05:20.9665540Z",
    "PublishedUtc": "2020-04-20T15:05:20.9665540Z",
    "CreatedUtc": "2020-04-20T15:05:20.9665540Z",
    "Owner": "admin",
    "Author": "admin"
  },
  {
    "TitlePart": {
      "Title": "Administration"
    },
    "JobCategory": {
      "Description": {
        "Html": "\u003Cp\u003EAdministration\u003C/p\u003E"
      },
      "WebsiteURI": {
        "Text": "/job-categories/administration"
      },
      "JobProfiles": {
        "ContentItemIds": [
          "4gtkebzsg9e21478jffakzjew4",
          "4jh01tv2rezp7ray1dqyw2ka45",
          "4ysjhfx5w5jtm5qdskt8scajx7"
        ]
      }
    },
    "GraphSyncPart": {
      "Text": "http://nationalcareers.service.gov.uk/jobcategory/7f1102c3-1140-4677-a452-07bb702e9a11"
    },
    "ContentItemId": "40njysqq5h0pm3qrg0b8hebwdm",
    "ContentItemVersionId": "4tbbxtpyf9d02yc18q1m72nqnm",
    "ContentType": "JobCategory",
    "DisplayText": "Administration",
    "Latest": true,
    "Published": true,
    "ModifiedUtc": "2020-04-20T15:05:20.9665540Z",
    "PublishedUtc": "2020-04-20T15:05:20.9665540Z",
    "CreatedUtc": "2020-04-20T15:05:20.9665540Z",
    "Owner": "admin",
    "Author": "admin"
  },
  {
    "TitlePart": {
      "Title": "Managerial"
    },
    "JobCategory": {
      "Description": {
        "Html": "\u003Cp\u003EManagerial\u003C/p\u003E"
      },
      "WebsiteURI": {
        "Text": "/job-categories/managerial"
      },
      "JobProfiles": {
        "ContentItemIds": [
          "4x3gbz5kwsashxyszhz7symkmd",
          "4jh01tv2rezp7ray1dqyw2ka45"
        ]
      }
    },
    "GraphSyncPart": {
      "Text": "http://nationalcareers.service.gov.uk/jobcategory/2a8af75f-51cf-4331-845c-f3d423903dcb"
    },
    "ContentItemId": "46253yrjck3js4a3cmpeahmjm3",
    "ContentItemVersionId": "40p8r7sanp2yx58zwxsh7z9a5r",
    "ContentType": "JobCategory",
    "DisplayText": "Managerial",
    "Latest": true,
    "Published": true,
    "ModifiedUtc": "2020-04-20T15:05:20.9665540Z",
    "PublishedUtc": "2020-04-20T15:05:20.9665540Z",
    "CreatedUtc": "2020-04-20T15:05:20.9665540Z",
    "Owner": "admin",
    "Author": "admin"
  },
  {
    "TitlePart": {
      "Title": "Creative and media"
    },
    "JobCategory": {
      "Description": {
        "Html": "\u003Cp\u003ECreative and media\u003C/p\u003E"
      },
      "WebsiteURI": {
        "Text": "/job-categories/creative-and-media"
      },
      "JobProfiles": {
        "ContentItemIds": []
      }
    },
    "GraphSyncPart": {
      "Text": "http://nationalcareers.service.gov.uk/jobcategory/6d87286d-936f-464a-be9a-8ccf6123179f"
    },
    "ContentItemId": "4qtxmcg8h74w63kd682y0816m4",
    "ContentItemVersionId": "47hfb4hfa6apy0kpax7ejhmax5",
    "ContentType": "JobCategory",
    "DisplayText": "Creative and media",
    "Latest": true,
    "Published": true,
    "ModifiedUtc": "2020-04-20T15:05:20.9665540Z",
    "PublishedUtc": "2020-04-20T15:05:20.9665540Z",
    "CreatedUtc": "2020-04-20T15:05:20.9665540Z",
    "Owner": "admin",
    "Author": "admin"
  },
  {
    "TitlePart": {
      "Title": "Retail and sales"
    },
    "JobCategory": {
      "Description": {
        "Html": "\u003Cp\u003ERetail and sales\u003C/p\u003E"
      },
      "WebsiteURI": {
        "Text": "/job-categories/retail-and-sales"
      },
      "JobProfiles": {
        "ContentItemIds": [
          "4nsn7bz20vs7cs852cybw2mhd2",
          "434waqsbt44tt46ava4zybkqcp",
          "4kqn90q59csetznqdpt2w8qxcj"
        ]
      }
    },
    "GraphSyncPart": {
      "Text": "http://nationalcareers.service.gov.uk/jobcategory/91eacad2-8a0f-4243-9768-1672da280415"
    },
    "ContentItemId": "476ey6exywq1457z0a9n0e7v46",
    "ContentItemVersionId": "4j6sn9e0x3ya10rv1dmr72yj40",
    "ContentType": "JobCategory",
    "DisplayText": "Retail and sales",
    "Latest": true,
    "Published": true,
    "ModifiedUtc": "2020-04-20T15:05:20.9665540Z",
    "PublishedUtc": "2020-04-20T15:05:20.9665540Z",
    "CreatedUtc": "2020-04-20T15:05:20.9665540Z",
    "Owner": "admin",
    "Author": "admin"
  },
  {
    "TitlePart": {
      "Title": "Government services"
    },
    "JobCategory": {
      "Description": {
        "Html": "\u003Cp\u003EGovernment services\u003C/p\u003E"
      },
      "WebsiteURI": {
        "Text": "/job-categories/government-services"
      },
      "JobProfiles": {
        "ContentItemIds": [
          "4gtkebzsg9e21478jffakzjew4"
        ]
      }
    },
    "GraphSyncPart": {
      "Text": "http://nationalcareers.service.gov.uk/jobcategory/298515ac-c131-43e2-b6d3-28127033edbe"
    },
    "ContentItemId": "4xw1cb5bt836hw5xpspba7tacj",
    "ContentItemVersionId": "44we2nfk699nm06m2xmzcypect",
    "ContentType": "JobCategory",
    "DisplayText": "Government services",
    "Latest": true,
    "Published": true,
    "ModifiedUtc": "2020-04-20T15:05:20.9665540Z",
    "PublishedUtc": "2020-04-20T15:05:20.9665540Z",
    "CreatedUtc": "2020-04-20T15:05:20.9665540Z",
    "Owner": "admin",
    "Author": "admin"
  },
  {
    "TitlePart": {
      "Title": "Transport"
    },
    "JobCategory": {
      "Description": {
        "Html": "\u003Cp\u003ETransport\u003C/p\u003E"
      },
      "WebsiteURI": {
        "Text": "/job-categories/transport"
      },
      "JobProfiles": {
        "ContentItemIds": [
          "4nsn7bz20vs7cs852cybw2mhd2",
          "4th3pvtj6k615wbb0prswp5dwd"
        ]
      }
    },
    "GraphSyncPart": {
      "Text": "http://nationalcareers.service.gov.uk/jobcategory/f5ac424c-59dc-440e-9a7b-8291b4785ba2"
    },
    "ContentItemId": "4t0v8bjs2en1y26rash6tkk3dm",
    "ContentItemVersionId": "4wfxpsty0zckp77fcdp4xdbfm9",
    "ContentType": "JobCategory",
    "DisplayText": "Transport",
    "Latest": true,
    "Published": true,
    "ModifiedUtc": "2020-04-20T15:05:20.9665540Z",
    "PublishedUtc": "2020-04-20T15:05:20.9665540Z",
    "CreatedUtc": "2020-04-20T15:05:20.9665540Z",
    "Owner": "admin",
    "Author": "admin"
  },
  {
    "TitlePart": {
      "Title": "Science and research"
    },
    "JobCategory": {
      "Description": {
        "Html": "\u003Cp\u003EScience and research\u003C/p\u003E"
      },
      "WebsiteURI": {
        "Text": "/job-categories/science-and-research"
      },
      "JobProfiles": {
        "ContentItemIds": []
      }
    },
    "GraphSyncPart": {
      "Text": "http://nationalcareers.service.gov.uk/jobcategory/ee618732-b120-46be-acd8-185be5b1b54c"
    },
    "ContentItemId": "4czq0q4q3r69ewy6ywjn1r7kcn",
    "ContentItemVersionId": "4wncktb3t0ka7wzehndargemd5",
    "ContentType": "JobCategory",
    "DisplayText": "Science and research",
    "Latest": true,
    "Published": true,
    "ModifiedUtc": "2020-04-20T15:05:20.9665540Z",
    "PublishedUtc": "2020-04-20T15:05:20.9665540Z",
    "CreatedUtc": "2020-04-20T15:05:20.9665540Z",
    "Owner": "admin",
    "Author": "admin"
  },
  {
    "TitlePart": {
      "Title": "Healthcare"
    },
    "JobCategory": {
      "Description": {
        "Html": "\u003Cp\u003EHealthcare\u003C/p\u003E"
      },
      "WebsiteURI": {
        "Text": "/job-categories/healthcare"
      },
      "JobProfiles": {
        "ContentItemIds": [
          "47y6mkth2092p0f7ak0vsmvd5g",
          "434waqsbt44tt46ava4zybkqcp"
        ]
      }
    },
    "GraphSyncPart": {
      "Text": "http://nationalcareers.service.gov.uk/jobcategory/1367ba26-0420-4e57-8560-5557ac6668ea"
    },
    "ContentItemId": "4kyrj9b908kvn6m1taa9f50945",
    "ContentItemVersionId": "4e3eberfn9rxyywkfsh0yghem7",
    "ContentType": "JobCategory",
    "DisplayText": "Healthcare",
    "Latest": true,
    "Published": true,
    "ModifiedUtc": "2020-04-20T15:05:20.9665540Z",
    "PublishedUtc": "2020-04-20T15:05:20.9665540Z",
    "CreatedUtc": "2020-04-20T15:05:20.9665540Z",
    "Owner": "admin",
    "Author": "admin"
  },
  {
    "TitlePart": {
      "Title": "Home services"
    },
    "JobCategory": {
      "Description": {
        "Html": "\u003Cp\u003EHome services\u003C/p\u003E"
      },
      "WebsiteURI": {
        "Text": "/job-categories/home-services"
      },
      "JobProfiles": {
        "ContentItemIds": [
          "47y6mkth2092p0f7ak0vsmvd5g",
          "4805a6srhfw4mrmyafbraae2xv"
        ]
      }
    },
    "GraphSyncPart": {
      "Text": "http://nationalcareers.service.gov.uk/jobcategory/2b9e70c8-a6d3-449f-b504-2fc2d45a3446"
    },
    "ContentItemId": "4j1h8g1zkx258z7xabxsk3t456",
    "ContentItemVersionId": "4fqbv7f1b5jkav07b528s84hm8",
    "ContentType": "JobCategory",
    "DisplayText": "Home services",
    "Latest": true,
    "Published": true,
    "ModifiedUtc": "2020-04-20T15:05:20.9665540Z",
    "PublishedUtc": "2020-04-20T15:05:20.9665540Z",
    "CreatedUtc": "2020-04-20T15:05:20.9665540Z",
    "Owner": "admin",
    "Author": "admin"
  },
  {
    "TitlePart": {
      "Title": "Social care"
    },
    "JobCategory": {
      "Description": {
        "Html": "\u003Cp\u003ESocial care\u003C/p\u003E"
      },
      "WebsiteURI": {
        "Text": "/job-categories/social-care"
      },
      "JobProfiles": {
        "ContentItemIds": [
          "47y6mkth2092p0f7ak0vsmvd5g",
          "4zx0nqaeseasp6c8f7z29qgkcv"
        ]
      }
    },
    "GraphSyncPart": {
      "Text": "http://nationalcareers.service.gov.uk/jobcategory/2ea3674e-308b-48e0-968b-0b3064b8be85"
    },
    "ContentItemId": "4pjstbh93rkcv3nrxvm6y88bx0",
    "ContentItemVersionId": "4hrcnfwgvs6hz680qk5w7gp1xx",
    "ContentType": "JobCategory",
    "DisplayText": "Social care",
    "Latest": true,
    "Published": true,
    "ModifiedUtc": "2020-04-20T15:05:20.9665540Z",
    "PublishedUtc": "2020-04-20T15:05:20.9665540Z",
    "CreatedUtc": "2020-04-20T15:05:20.9665540Z",
    "Owner": "admin",
    "Author": "admin"
  },
  {
    "TitlePart": {
      "Title": "Environment and land"
    },
    "JobCategory": {
      "Description": {
        "Html": "\u003Cp\u003EEnvironment and land\u003C/p\u003E"
      },
      "WebsiteURI": {
        "Text": "/job-categories/environment-and-land"
      },
      "JobProfiles": {
        "ContentItemIds": [
          "4x3gbz5kwsashxyszhz7symkmd"
        ]
      }
    },
    "GraphSyncPart": {
      "Text": "http://nationalcareers.service.gov.uk/jobcategory/c263d4ae-713c-4a95-a46e-6f5d7c1662b6"
    },
    "ContentItemId": "4jz52aztw7apzz76mac7ynj85t",
    "ContentItemVersionId": "42ypwqgdzmr187rknx78bfgz41",
    "ContentType": "JobCategory",
    "DisplayText": "Environment and land",
    "Latest": true,
    "Published": true,
    "ModifiedUtc": "2020-04-20T15:05:20.9665540Z",
    "PublishedUtc": "2020-04-20T15:05:20.9665540Z",
    "CreatedUtc": "2020-04-20T15:05:20.9665540Z",
    "Owner": "admin",
    "Author": "admin"
  },
  {
    "TitlePart": {
      "Title": "Travel and tourism"
    },
    "JobCategory": {
      "Description": {
        "Html": "\u003Cp\u003ETravel and tourism\u003C/p\u003E"
      },
      "WebsiteURI": {
        "Text": "/job-categories/travel-and-tourism"
      },
      "JobProfiles": {
        "ContentItemIds": [
          "4nsn7bz20vs7cs852cybw2mhd2"
        ]
      }
    },
    "GraphSyncPart": {
      "Text": "http://nationalcareers.service.gov.uk/jobcategory/f37ddabf-1bdc-4cc6-9866-01b76ad963b6"
    },
    "ContentItemId": "400654cvqsvhn3w81xrjq03fmz",
    "ContentItemVersionId": "4165r4k2bf85yxdg97atvfxa5w",
    "ContentType": "JobCategory",
    "DisplayText": "Travel and tourism",
    "Latest": true,
    "Published": true,
    "ModifiedUtc": "2020-04-20T15:05:20.9665540Z",
    "PublishedUtc": "2020-04-20T15:05:20.9665540Z",
    "CreatedUtc": "2020-04-20T15:05:20.9665540Z",
    "Owner": "admin",
    "Author": "admin"
  },
  {
    "TitlePart": {
      "Title": "Animal care"
    },
    "JobCategory": {
      "Description": {
        "Html": "\u003Cp\u003EAnimal care\u003C/p\u003E"
      },
      "WebsiteURI": {
        "Text": "/job-categories/animal-care"
      },
      "JobProfiles": {
        "ContentItemIds": [
          "4x3gbz5kwsashxyszhz7symkmd"
        ]
      }
    },
    "GraphSyncPart": {
      "Text": "http://nationalcareers.service.gov.uk/jobcategory/01032616-6892-4086-8857-3537b61fa6d0"
    },
    "ContentItemId": "4ghksy57j7x6d6je5tjy9caxxt",
    "ContentItemVersionId": "4yds9mbsgbsxztww5ztxa26en1",
    "ContentType": "JobCategory",
    "DisplayText": "Animal care",
    "Latest": true,
    "Published": true,
    "ModifiedUtc": "2020-04-20T15:05:20.9665540Z",
    "PublishedUtc": "2020-04-20T15:05:20.9665540Z",
    "CreatedUtc": "2020-04-20T15:05:20.9665540Z",
    "Owner": "admin",
    "Author": "admin"
  },
  {
    "TitlePart": {
      "Title": "Construction and trades"
    },
    "JobCategory": {
      "Description": {
        "Html": "\u003Cp\u003EConstruction and trades\u003C/p\u003E"
      },
      "WebsiteURI": {
        "Text": "/job-categories/construction-and-trades"
      },
      "JobProfiles": {
        "ContentItemIds": [
          "4q2ee6g4va0935x5zt6px9hw4k",
          "4c6160fpj2f2v0k5ksksjpmq41",
          "4rwsas55d999gzx5asgc2s9nc1"
        ]
      }
    },
    "GraphSyncPart": {
      "Text": "http://nationalcareers.service.gov.uk/jobcategory/c4a968ba-c81e-48ef-b156-82e10e84266d"
    },
    "ContentItemId": "41j0dyadgffw4wpcjw5bmg8253",
    "ContentItemVersionId": "4nr6vt2f0gznq1rqsw6h4ps0xs",
    "ContentType": "JobCategory",
    "DisplayText": "Construction and trades",
    "Latest": true,
    "Published": true,
    "ModifiedUtc": "2020-04-20T15:05:20.9665540Z",
    "PublishedUtc": "2020-04-20T15:05:20.9665540Z",
    "CreatedUtc": "2020-04-20T15:05:20.9665540Z",
    "Owner": "admin",
    "Author": "admin"
  },
  {
    "TitlePart": {
      "Title": "Teaching and education"
    },
    "JobCategory": {
      "Description": {
        "Html": "\u003Cp\u003ETeaching and education\u003C/p\u003E"
      },
      "WebsiteURI": {
        "Text": "/job-categories/teaching-and-education"
      },
      "JobProfiles": {
        "ContentItemIds": [
          "4hsbk0z172ejs3h9rxfhnzx2dv"
        ]
      }
    },
    "GraphSyncPart": {
      "Text": "http://nationalcareers.service.gov.uk/jobcategory/28c67e6a-6c9f-420f-8b9d-a76e75de6720"
    },
    "ContentItemId": "4apgjngzdnz2w0emfg78sjgdx1",
    "ContentItemVersionId": "4sskv0ygaydpbwch08bxrepgx4",
    "ContentType": "JobCategory",
    "DisplayText": "Teaching and education",
    "Latest": true,
    "Published": true,
    "ModifiedUtc": "2020-04-20T15:05:20.9665540Z",
    "PublishedUtc": "2020-04-20T15:05:20.9665540Z",
    "CreatedUtc": "2020-04-20T15:05:20.9665540Z",
    "Owner": "admin",
    "Author": "admin"
  },
  {
    "TitlePart": {
      "Title": "Business and finance"
    },
    "JobCategory": {
      "Description": {
        "Html": "\u003Cp\u003EBusiness and finance\u003C/p\u003E"
      },
      "WebsiteURI": {
        "Text": "/job-categories/business-and-finance"
      },
      "JobProfiles": {
        "ContentItemIds": []
      }
    },
    "GraphSyncPart": {
      "Text": "http://nationalcareers.service.gov.uk/jobcategory/59c14dd9-b055-4af1-87bf-0967a087287c"
    },
    "ContentItemId": "41wsqzv0tstmnyjryp0spqbbwm",
    "ContentItemVersionId": "4r95gg7ya7vfgrkqk4ce7zj7mg",
    "ContentType": "JobCategory",
    "DisplayText": "Business and finance",
    "Latest": true,
    "Published": true,
    "ModifiedUtc": "2020-04-20T15:05:20.9665540Z",
    "PublishedUtc": "2020-04-20T15:05:20.9665540Z",
    "CreatedUtc": "2020-04-20T15:05:20.9665540Z",
    "Owner": "admin",
    "Author": "admin"
  },
  {
    "TitlePart": {
      "Title": "Computing"
    },
    "JobCategory": {
      "Description": {
        "Html": "\u003Cp\u003EComputing\u003C/p\u003E"
      },
      "WebsiteURI": {
        "Text": "/job-categories/computing"
      },
      "JobProfiles": {
        "ContentItemIds": []
      }
    },
    "GraphSyncPart": {
      "Text": "http://nationalcareers.service.gov.uk/jobcategory/59a18da1-346b-4456-a33c-342e08036313"
    },
    "ContentItemId": "4rrg2v2ptgknt3f3e5nscxev5c",
    "ContentItemVersionId": "4ak1s7yw3tpaerg9xefn95nqnc",
    "ContentType": "JobCategory",
    "DisplayText": "Computing",
    "Latest": true,
    "Published": true,
    "ModifiedUtc": "2020-04-20T15:05:20.9665540Z",
    "PublishedUtc": "2020-04-20T15:05:20.9665540Z",
    "CreatedUtc": "2020-04-20T15:05:20.9665540Z",
    "Owner": "admin",
    "Author": "admin"
  },
  {
    "TitlePart": {
      "Title": " technology and digital"
    },
    "JobCategory": {
      "Description": {
        "Html": "\u003Cp\u003E technology and digital\u003C/p\u003E"
      },
      "WebsiteURI": {
        "Text": "/job-categories/-technology-and-digital"
      },
      "JobProfiles": {
        "ContentItemIds": []
      }
    },
    "GraphSyncPart": {
      "Text": "http://nationalcareers.service.gov.uk/jobcategory/ac9107df-4cb1-4b94-85d5-be5e46cab0e7"
    },
    "ContentItemId": "45gx8z66mb2q80bav7xm110cwq",
    "ContentItemVersionId": "42ea7v36zc5pgwvtc9nj1ks3wj",
    "ContentType": "JobCategory",
    "DisplayText": " technology and digital",
    "Latest": true,
    "Published": true,
    "ModifiedUtc": "2020-04-20T15:05:20.9665540Z",
    "PublishedUtc": "2020-04-20T15:05:20.9665540Z",
    "CreatedUtc": "2020-04-20T15:05:20.9665540Z",
    "Owner": "admin",
    "Author": "admin"
  },
  {
    "TitlePart": {
      "Title": "Law and legal"
    },
    "JobCategory": {
      "Description": {
        "Html": "\u003Cp\u003ELaw and legal\u003C/p\u003E"
      },
      "WebsiteURI": {
        "Text": "/job-categories/law-and-legal"
      },
      "JobProfiles": {
        "ContentItemIds": []
      }
    },
    "GraphSyncPart": {
      "Text": "http://nationalcareers.service.gov.uk/jobcategory/36b26f13-2b48-4e8a-bc8f-864a1ddc6df8"
    },
    "ContentItemId": "44n1fgsv2mgrvsmh2zdqj6hpww",
    "ContentItemVersionId": "4xyfjgq8e6x3y0q6rx6k87h14q",
    "ContentType": "JobCategory",
    "DisplayText": "Law and legal",
    "Latest": true,
    "Published": true,
    "ModifiedUtc": "2020-04-20T15:05:20.9665540Z",
    "PublishedUtc": "2020-04-20T15:05:20.9665540Z",
    "CreatedUtc": "2020-04-20T15:05:20.9665540Z",
    "Owner": "admin",
    "Author": "admin"
  },
  {
    "TitlePart": {
      "Title": "Delivery and storage"
    },
    "JobCategory": {
      "Description": {
        "Html": "\u003Cp\u003EDelivery and storage\u003C/p\u003E"
      },
      "WebsiteURI": {
        "Text": "/job-categories/delivery-and-storage"
      },
      "JobProfiles": {
        "ContentItemIds": [
          "4805a6srhfw4mrmyafbraae2xv"
        ]
      }
    },
    "GraphSyncPart": {
      "Text": "http://nationalcareers.service.gov.uk/jobcategory/580f501d-df26-43c6-b29d-3d182bdd0b53"
    },
    "ContentItemId": "4wnhr41g4texgsa94xxw4tt64h",
    "ContentItemVersionId": "418xe80fvrwr760ch9zqgf5pnx",
    "ContentType": "JobCategory",
    "DisplayText": "Delivery and storage",
    "Latest": true,
    "Published": true,
    "ModifiedUtc": "2020-04-20T15:05:20.9665540Z",
    "PublishedUtc": "2020-04-20T15:05:20.9665540Z",
    "CreatedUtc": "2020-04-20T15:05:20.9665540Z",
    "Owner": "admin",
    "Author": "admin"
  },
  {
    "TitlePart": {
      "Title": "Emergency and uniform services"
    },
    "JobCategory": {
      "Description": {
        "Html": "\u003Cp\u003EEmergency and uniform services\u003C/p\u003E"
      },
      "WebsiteURI": {
        "Text": "/job-categories/emergency-and-uniform-services"
      },
      "JobProfiles": {
        "ContentItemIds": [
          "4gtkebzsg9e21478jffakzjew4"
        ]
      }
    },
    "GraphSyncPart": {
      "Text": "http://nationalcareers.service.gov.uk/jobcategory/50af54fb-a511-47a4-9533-1b0caa54e17f"
    },
    "ContentItemId": "4dd96c1y5cbywxqp0snbxg3ydp",
    "ContentItemVersionId": "4bds92qpmcs0z372fj9xb37gxj",
    "ContentType": "JobCategory",
    "DisplayText": "Emergency and uniform services",
    "Latest": true,
    "Published": true,
    "ModifiedUtc": "2020-04-20T15:05:20.9665540Z",
    "PublishedUtc": "2020-04-20T15:05:20.9665540Z",
    "CreatedUtc": "2020-04-20T15:05:20.9665540Z",
    "Owner": "admin",
    "Author": "admin"
  }
      ]
    }
  ]
}