{
  "name": "Registrations0_2ae99ef3-1cab-4246-b55f-cdc6c6646dc1",
  "displayName": "Registrations0_2ae99ef3-1cab-4246-b55f-cdc6c6646dc1",
  "description": "",
  "author": "",
  "website": "",
  "version": "",
  "issetuprecipe": false,
  "categories": "",
  "tags": [],
  "steps": [
    {
      "name": "ContentNoCache",
      "data": [
  {
    "TitlePart": {
      "Title": "QTS"
    },
    "Registration": {
      "Description": {
        "Html": "\u003Cp\u003Eyou\u0027ll usually need \u003Ca href=\u0022https://www.gov.uk/guidance/qualified-teacher-status-qts\u0022\u003Equalified teacher status\u003C/a\u003E (QTS) to teach in a state school in England\u003C/p\u003E"
      }
    },
    "GraphSyncPart": {
      "Text": "[js:configuration(\u0027ContentApiPrefix\u0027).toLowerCase() \u002B \u0027/registration/bcee09ef-896e-414a-82b4-b3eeff5549fc\u0027]"
    },
    "ContentItemId": "40eyn5nw1cv9y4e0g3myg0prnp",
    "ContentItemVersionId": "49tp370c4mc1wvzx2z5v22z5wc",
    "ContentType": "Registration",
    "DisplayText": "QTS",
    "Latest": true,
    "Published": true,
    "ModifiedUtc": "2020-06-17T09:20:07.1376452Z",
    "PublishedUtc": "2020-06-17T09:20:07.1376452Z",
    "CreatedUtc": "2020-06-17T09:20:07.1376452Z",
    "Owner": "admin",
    "Author": "admin"
  },
  {
    "TitlePart": {
      "Title": "HCPC"
    },
    "Registration": {
      "Description": {
        "Html": "\u003Cp\u003Eyou\u0027ll need to register with the \u003Ca href=\u0022http://www.hcpc-uk.co.uk/\u0022\u003EHealth and Care Professions Council\u003C/a\u003E\u003C/p\u003E"
      }
    },
    "GraphSyncPart": {
      "Text": "[js:configuration(\u0027ContentApiPrefix\u0027).toLowerCase() \u002B \u0027/registration/5acc67f0-746d-4a4a-b5d6-f784690e096c\u0027]"
    },
    "ContentItemId": "4an66j9znzcfpt2zq38reyphm6",
    "ContentItemVersionId": "4kgv9vmh434wq4b97rqf4wk2dx",
    "ContentType": "Registration",
    "DisplayText": "HCPC",
    "Latest": true,
    "Published": true,
    "ModifiedUtc": "2020-06-17T09:20:07.1376452Z",
    "PublishedUtc": "2020-06-17T09:20:07.1376452Z",
    "CreatedUtc": "2020-06-17T09:20:07.1376452Z",
    "Owner": "admin",
    "Author": "admin"
  },
  {
    "TitlePart": {
      "Title": "CSCS"
    },
    "Registration": {
      "Description": {
        "Html": "\u003Cp\u003Eyou\u0027ll need a \u003Ca href=\u0022https://www.cscs.uk.com\u0022\u003EConstruction Skills Certification Scheme\u003C/a\u003E (CSCS) card or equivalent to train and work on a construction site\u003C/p\u003E"
      }
    },
    "GraphSyncPart": {
      "Text": "[js:configuration(\u0027ContentApiPrefix\u0027).toLowerCase() \u002B \u0027/registration/252b61d1-6a31-4506-982e-5be3e7e2a96c\u0027]"
    },
    "ContentItemId": "4tbavfd00p0za11grn604da7dp",
    "ContentItemVersionId": "4sz1j96maqbyhy721qvdj744m2",
    "ContentType": "Registration",
    "DisplayText": "CSCS",
    "Latest": true,
    "Published": true,
    "ModifiedUtc": "2020-06-17T09:20:07.1376452Z",
    "PublishedUtc": "2020-06-17T09:20:07.1376452Z",
    "CreatedUtc": "2020-06-17T09:20:07.1376452Z",
    "Owner": "admin",
    "Author": "admin"
  }
      ]
    }
  ]
}