[{"Type":"ApprenticeshipLink","ExistingTitle":"guide to apprenticeships"},{"Type":"ApprenticeshipLink","ExistingTitle":"postgraduate teaching apprenticeships"},{"Type":"ApprenticeshipLink","ExistingTitle":"equivalent entry requirements"},{"Type":"ApprenticeshipLink","ExistingTitle":"guide to apprenticeships"},{"Type":"ApprenticeshipLink","ExistingTitle":"postgraduate teaching apprenticeships"},{"Type":"ApprenticeshipLink","ExistingTitle":"equivalent entry requirements"},{"Type":"ApprenticeshipRequirement","ExistingTitle":"GCSE science at grade 9 to 4 (A* to C) for primary school teaching"},{"Type":"ApprenticeshipRequirement","ExistingTitle":"GCSEs at grades 9 to 4 (A* to C) in English and maths"},{"Type":"ApprenticeshipRequirement","ExistingTitle":"a degree for a teaching apprenticeship"},{"Type":"ApprenticeshipRequirement","ExistingTitle":"4 or 5 GCSEs at grades 9 to 4 (A* to C) and A levels, or equivalent, for a higher or degree apprenticeship"},{"Type":"ApprenticeshipRequirement","ExistingTitle":"5 GCSEs at grades 9 to 4 (A* to C), or equivalent, including English and maths, for an advanced apprenticeship"},{"Type":"ApprenticeshipRequirement","ExistingTitle":"some GCSEs, usually including English and maths, or equivalent, for an intermediate apprenticeship"},{"Type":"ApprenticeshipRequirement","ExistingTitle":"4 or 5 GCSEs at grades 9 to 4 (A* to C) and A levels, or equivalent, for a degree apprenticeship"},{"Type":"ApprenticeshipRequirement","ExistingTitle":"2 or more GCSEs at grades 9 to 4 (A* to C), or equivalent, including English and maths"},{"Type":"ApprenticeshipRequirement","ExistingTitle":"GCSE science at grade 9 to 4 (A* to C) for primary school teaching"},{"Type":"ApprenticeshipRequirement","ExistingTitle":"GCSEs at grades 9 to 4 (A* to C) in English and maths"},{"Type":"ApprenticeshipRequirement","ExistingTitle":"a degree for a teaching apprenticeship"},{"Type":"ApprenticeshipRequirement","ExistingTitle":"4 or 5 GCSEs at grades 9 to 4 (A* to C) and A levels, or equivalent, for a higher or degree apprenticeship"},{"Type":"ApprenticeshipRequirement","ExistingTitle":"5 GCSEs at grades 9 to 4 (A* to C), or equivalent, including English and maths, for an advanced apprenticeship"},{"Type":"ApprenticeshipRequirement","ExistingTitle":"some GCSEs, usually including English and maths, or equivalent, for an intermediate apprenticeship"},{"Type":"ApprenticeshipRequirement","ExistingTitle":"4 or 5 GCSEs at grades 9 to 4 (A* to C) and A levels, or equivalent, for a degree apprenticeship"},{"Type":"ApprenticeshipRequirement","ExistingTitle":"2 or more GCSEs at grades 9 to 4 (A* to C), or equivalent, including English and maths"},{"Type":"CollegeLink","ExistingTitle":"funding advice for higher education courses in college"},{"Type":"CollegeLink","ExistingTitle":"search for courses"},{"Type":"CollegeLink","ExistingTitle":"funding advice"},{"Type":"CollegeLink","ExistingTitle":"search for agricultural colleges"},{"Type":"CollegeLink","ExistingTitle":"equivalent entry requirements"},{"Type":"CollegeLink","ExistingTitle":"funding advice for higher education courses in college"},{"Type":"CollegeLink","ExistingTitle":"search for courses"},{"Type":"CollegeLink","ExistingTitle":"funding advice"},{"Type":"CollegeLink","ExistingTitle":"search for agricultural colleges"},{"Type":"CollegeLink","ExistingTitle":"equivalent entry requirements"},{"Type":"CollegeRequirement","ExistingTitle":"4 or 5 GCSEs at grades 9 to 4 (A* to C), or equivalent, for a level 3 course"},{"Type":"CollegeRequirement","ExistingTitle":"1 or 2 A levels, a level 3 diploma or relevant experience for a level 4 or level 5 course"},{"Type":"CollegeRequirement","ExistingTitle":"2 or fewer GCSEs at grades 3 to 1 (D to G), or equivalent, for a level 1 course"},{"Type":"CollegeRequirement","ExistingTitle":"1 or 2 A levels, or equivalent, for a higher national certificate or higher national diploma"},{"Type":"CollegeRequirement","ExistingTitle":"2 or more GCSEs at grades 9 to 3 (A* to D), or equivalent, for a level 2 course"},{"Type":"CollegeRequirement","ExistingTitle":"4 or 5 GCSEs at grades 9 to 4 (A* to C), or equivalent, for a level 3 course"},{"Type":"CollegeRequirement","ExistingTitle":"1 or 2 A levels, a level 3 diploma or relevant experience for a level 4 or level 5 course"},{"Type":"CollegeRequirement","ExistingTitle":"2 or fewer GCSEs at grades 3 to 1 (D to G), or equivalent, for a level 1 course"},{"Type":"CollegeRequirement","ExistingTitle":"1 or 2 A levels, or equivalent, for a higher national certificate or higher national diploma"},{"Type":"CollegeRequirement","ExistingTitle":"2 or more GCSEs at grades 9 to 3 (A* to D), or equivalent, for a level 2 course"},{"Type":"UniversityLink","ExistingTitle":"funding for teacher training"},{"Type":"UniversityLink","ExistingTitle":"search for conservatoire courses"},{"Type":"UniversityLink","ExistingTitle":"student finance for fees and living costs"},{"Type":"UniversityLink","ExistingTitle":"postgraduate teacher training courses"},{"Type":"UniversityLink","ExistingTitle":"equivalent entry requirements"},{"Type":"UniversityLink","ExistingTitle":"university courses and entry requirements"},{"Type":"UniversityLink","ExistingTitle":"funding for teacher training"},{"Type":"UniversityLink","ExistingTitle":"search for conservatoire courses"},{"Type":"UniversityLink","ExistingTitle":"student finance for fees and living costs"},{"Type":"UniversityLink","ExistingTitle":"postgraduate teacher training courses"},{"Type":"UniversityLink","ExistingTitle":"equivalent entry requirements"},{"Type":"UniversityLink","ExistingTitle":"university courses and entry requirements"},{"Type":"UniversityRequirement","ExistingTitle":"a degree in a relevant subject for postgraduate study"},{"Type":"UniversityRequirement","ExistingTitle":"2 to 3 A levels, or equivalent, for a degree"},{"Type":"UniversityRequirement","ExistingTitle":"to pass an audition"},{"Type":"UniversityRequirement","ExistingTitle":"2 or 3 A levels, or equivalent, including maths and a science for a degree"},{"Type":"UniversityRequirement","ExistingTitle":"1 or 2 A levels, or equivalent, for a foundation degree or higher national diploma"},{"Type":"UniversityRequirement","ExistingTitle":"a degree in any subject for a postgraduate course"},{"Type":"UniversityRequirement","ExistingTitle":"5 GCSEs at grades 9 to 4 (A* to C), or equivalent, including English, maths and science"},{"Type":"UniversityRequirement","ExistingTitle":"a degree in a relevant subject for postgraduate study"},{"Type":"UniversityRequirement","ExistingTitle":"2 to 3 A levels, or equivalent, for a degree"},{"Type":"UniversityRequirement","ExistingTitle":"to pass an audition"},{"Type":"UniversityRequirement","ExistingTitle":"2 or 3 A levels, or equivalent, including maths and a science for a degree"},{"Type":"UniversityRequirement","ExistingTitle":"1 or 2 A levels, or equivalent, for a foundation degree or higher national diploma"},{"Type":"UniversityRequirement","ExistingTitle":"a degree in any subject for a postgraduate course"},{"Type":"UniversityRequirement","ExistingTitle":"5 GCSEs at grades 9 to 4 (A* to C), or equivalent, including English, maths and science"},{"Type":"Registration","ExistingTitle":"you\u0027ll need to register with the \u003Ca href=\u0022http://www.hcpc-uk.co.uk/\u0022\u003EHealth and Care Professions Council\u003C/a\u003E"},{"Type":"Registration","ExistingTitle":"you\u0027ll need a \u003Ca href=\u0022https://www.cscs.uk.com\u0022\u003EConstruction Skills Certification Scheme\u003C/a\u003E (CSCS) card or equivalent to train and work on a construction site"},{"Type":"Registration","ExistingTitle":"you\u0027ll usually need \u003Ca href=\u0022https://www.gov.uk/guidance/qualified-teacher-status-qts\u0022\u003Equalified teacher status\u003C/a\u003E (QTS) to teach in a state school in England"},{"Type":"Registration","ExistingTitle":"you\u0027ll need to register with the \u003Ca href=\u0022http://www.hcpc-uk.co.uk/\u0022\u003EHealth and Care Professions Council\u003C/a\u003E"},{"Type":"Registration","ExistingTitle":"you\u0027ll need a \u003Ca href=\u0022https://www.cscs.uk.com\u0022\u003EConstruction Skills Certification Scheme\u003C/a\u003E (CSCS) card or equivalent to train and work on a construction site"},{"Type":"Registration","ExistingTitle":"you\u0027ll usually need \u003Ca href=\u0022https://www.gov.uk/guidance/qualified-teacher-status-qts\u0022\u003Equalified teacher status\u003C/a\u003E (QTS) to teach in a state school in England"},{"Type":"Restriction","ExistingTitle":"be over 18 years of age"},{"Type":"Restriction","ExistingTitle":"be over 20 years of age"},{"Type":"Restriction","ExistingTitle":"pass \u003Ca href=\u0022https://www.gov.uk/criminal-record-checks-apply-role\u0022\u003Ebackground checks\u003C/a\u003E"},{"Type":"Restriction","ExistingTitle":"be over 18 to sell alcohol and other restricted goods"},{"Type":"Restriction","ExistingTitle":"pass numeracy and literacy \u003Ca href=\u0022https://getintoteaching.education.gov.uk/post-teacher-training-application/preparing-for-the-professional-skills-tests\u0022\u003Eskills tests\u003C/a\u003E"},{"Type":"Restriction","ExistingTitle":"have a good level of fitness"},{"Type":"Restriction","ExistingTitle":"pass \u003Ca href=\u0022https://www.gov.uk/criminal-record-checks-apply-role\u0022\u003Eenhanced background checks\u003C/a\u003E"},{"Type":"Restriction","ExistingTitle":"have a full driving licence"},{"Type":"Restriction","ExistingTitle":"pass a medical check"},{"Type":"Restriction","ExistingTitle":"have lived in the UK for the last 5 years"},{"Type":"Restriction","ExistingTitle":"pass \u003Ca href=\u0022https://www.gov.uk/government/publications/national-security-vetting-advice-for-people-who-are-being-vetted\u0022\u003Esecurity checks\u003C/a\u003E"},{"Type":"Restriction","ExistingTitle":"be a UK, Republic of Ireland or Commonwealth citizen"},{"Type":"Restriction","ExistingTitle":"live within 1 hour\u0027s travel of the depot you\u0027re applying to"},{"Type":"Restriction","ExistingTitle":"be a UK citizen"},{"Type":"Restriction","ExistingTitle":"be over 18 years of age"},{"Type":"Restriction","ExistingTitle":"be over 20 years of age"},{"Type":"Restriction","ExistingTitle":"pass \u003Ca href=\u0022https://www.gov.uk/criminal-record-checks-apply-role\u0022\u003Ebackground checks\u003C/a\u003E"},{"Type":"Restriction","ExistingTitle":"be over 18 to sell alcohol and other restricted goods"},{"Type":"Restriction","ExistingTitle":"pass numeracy and literacy \u003Ca href=\u0022https://getintoteaching.education.gov.uk/post-teacher-training-application/preparing-for-the-professional-skills-tests\u0022\u003Eskills tests\u003C/a\u003E"},{"Type":"Restriction","ExistingTitle":"have a good level of fitness"},{"Type":"Restriction","ExistingTitle":"pass \u003Ca href=\u0022https://www.gov.uk/criminal-record-checks-apply-role\u0022\u003Eenhanced background checks\u003C/a\u003E"},{"Type":"Restriction","ExistingTitle":"have a full driving licence"},{"Type":"Restriction","ExistingTitle":"pass a medical check"},{"Type":"Restriction","ExistingTitle":"have lived in the UK for the last 5 years"},{"Type":"Restriction","ExistingTitle":"pass \u003Ca href=\u0022https://www.gov.uk/government/publications/national-security-vetting-advice-for-people-who-are-being-vetted\u0022\u003Esecurity checks\u003C/a\u003E"},{"Type":"Restriction","ExistingTitle":"be a UK, Republic of Ireland or Commonwealth citizen"},{"Type":"Restriction","ExistingTitle":"live within 1 hour\u0027s travel of the depot you\u0027re applying to"},{"Type":"Restriction","ExistingTitle":"be a UK citizen"},{"Type":"Environment","ExistingTitle":"physically demanding"},{"Type":"Environment","ExistingTitle":"physically and emotionally demanding"},{"Type":"Environment","ExistingTitle":"emotionally demanding"},{"Type":"Environment","ExistingTitle":"outdoors in all weathers"},{"Type":"Environment","ExistingTitle":"physically demanding"},{"Type":"Environment","ExistingTitle":"physically and emotionally demanding"},{"Type":"Environment","ExistingTitle":"emotionally demanding"},{"Type":"Environment","ExistingTitle":"outdoors in all weathers"},{"Type":"Location","ExistingTitle":"from a vehicle"},{"Type":"Location","ExistingTitle":"in a control room"},{"Type":"Location","ExistingTitle":"in an office"},{"Type":"Location","ExistingTitle":"on an aircraft"},{"Type":"Location","ExistingTitle":"at a restaurant"},{"Type":"Location","ExistingTitle":"on a construction site"},{"Type":"Location","ExistingTitle":"at a border post"},{"Type":"Location","ExistingTitle":"from a vehicle"},{"Type":"Location","ExistingTitle":"in a control room"},{"Type":"Location","ExistingTitle":"in an office"},{"Type":"Location","ExistingTitle":"on an aircraft"},{"Type":"Location","ExistingTitle":"at a restaurant"},{"Type":"Location","ExistingTitle":"on a construction site"},{"Type":"Location","ExistingTitle":"at a border post"},{"Type":"Uniform","ExistingTitle":"a uniform"},{"Type":"Uniform","ExistingTitle":"protective clothing"},{"Type":"Uniform","ExistingTitle":"a uniform"},{"Type":"Uniform","ExistingTitle":"protective clothing"}]